MANIFEST.in
README.md
requirements.txt
setup.py
tests-requirements.txt
django_memcached_consul/__init__.py
django_memcached_consul/memcached.py
django_memcached_consul.egg-info/PKG-INFO
django_memcached_consul.egg-info/SOURCES.txt
django_memcached_consul.egg-info/dependency_links.txt
django_memcached_consul.egg-info/requires.txt
django_memcached_consul.egg-info/top_level.txt
tests/__init__.py
tests/test_settings.py
tests/tests_memcached.py