Metadata-Version: 1.0
Name: django-memcached-consul
Version: 0.1.0
Summary: Django module that use consul to generate the list of memcached servers
Home-page: https://github.com/criteo/django-memcached-consul
Author: Criteo
Author-email: github@criteo.com
License: Apache Software License
Keywords: django memcached consul
Platform: UNKNOWN
